dockbuster/__init__.py
dockbuster/example.py
dockbuster-0.0.1.dist-info/entry_points.txt
dockbuster-0.0.1.dist-info/LICENSE
dockbuster-0.0.1.dist-info/WHEEL
dockbuster-0.0.1.dist-info/METADATA
dockbuster-0.0.1.dist-info/RECORD
