Metadata-Version: 2.1
Name: dockbuster
Version: 0.0.1
Summary: Command line tool and Python library for checking the chemical consistency and physical sensibility of docked ligands.
Keywords: dockbuster,docking,tests,metric
Author-email: Martin Buttenschoen <martin.buttenschoen@stats.ox.ac.uk>
Requires-Python: ~=3.7
Classifier: Development Status :: 3 - Alpha
Classifier: Topic :: Scientific/Engineering :: Bio-Informatics
Classifier: Intended Audience :: Science/Research
Classifier: License :: OSI Approved :: MIT License
Classifier: Programming Language :: Python :: 3 :: Only
Classifier: Programming Language :: Python :: 3.7
Classifier: Programming Language :: Python :: 3.8
Classifier: Programming Language :: Python :: 3.9
Classifier: Programming Language :: Python :: 3.10
Classifier: Programming Language :: Python :: 3.11
Classifier: Operating System :: OS Independent
Requires-Dist: rdkit >= 2020.09
Requires-Dist: pandas
Requires-Dist: numpy
Requires-Dist: tqdm
Requires-Dist: click ; extra == "cli"
Requires-Dist: isort ; extra == "dev"
Requires-Dist: black ; extra == "dev"
Requires-Dist: ipython ; extra == "docs"
Requires-Dist: nbsphinx ; extra == "docs"
Requires-Dist: sphinx_rtd_theme ; extra == "docs"
Requires-Dist: sphinx ; extra == "docs"
Requires-Dist: pre-commit ; extra == "test"
Requires-Dist: pytest ; extra == "test"
Requires-Dist: pytest-cov ; extra == "test"
Project-URL: Documentation, https://github.com/maabuu/dockbuster/tree/main#readme
Project-URL: Source, https://github.com/maabuu/dockbuster
Project-URL: Tracker, https://github.com/maabuu/dockbuster/issues
Provides-Extra: cli
Provides-Extra: dev
Provides-Extra: docs
Provides-Extra: test
